cursofiap/__init__.py
cursofiap/core.py
cursofiap_utils_luest-1.0.0.dist-info/METADATA
cursofiap_utils_luest-1.0.0.dist-info/WHEEL
cursofiap_utils_luest-1.0.0.dist-info/top_level.txt
cursofiap_utils_luest-1.0.0.dist-info/RECORD
