Metadata-Version: 2.4
Name: cursofiap-utils-luest
Version: 1.0.0
Summary: Descricao da sua lib cursofiap
Home-page: https://github.com/tadrianonet/luestevam
Author: Luciana Estevam
Author-email: luestevam@hotmail.com
License: MIT
Dynamic: author
Dynamic: author-email
Dynamic: description
Dynamic: description-content-type
Dynamic: home-page
Dynamic: license
Dynamic: summary
